psychometric/__init__.py
psychometric/exceptions.py
psychometric/item_analysis.py
psychometric/reliability.py
psychometric/utils.py
psychometric/validity.py
psychometric-0.1.0.dist-info/METADATA
psychometric-0.1.0.dist-info/WHEEL
psychometric-0.1.0.dist-info/top_level.txt
psychometric-0.1.0.dist-info/RECORD
