Metadata-Version: 2.4
Name: psychometric
Version: 0.1.0
Summary: Simple utils for psychometric computation
Author-email: Guohao Zhang <guohao2045@gmail.com>
Requires-Python: >=3.12
Requires-Dist: factor-analyzer>=0.5.1
Requires-Dist: numpy>=2.4.0
Requires-Dist: pandas>=2.3.3
Requires-Dist: pingouin>=0.5.5
Requires-Dist: semopy>=2.3.11
Requires-Dist: scikit-learn<1.6
Requires-Dist: scipy>=1.14.0
Requires-Dist: graphviz>=0.21
